odoo/addons/product_restrict_payment_acquirer/README.rst
odoo/addons/product_restrict_payment_acquirer/__init__.py
odoo/addons/product_restrict_payment_acquirer/__manifest__.py
odoo/addons/product_restrict_payment_acquirer/i18n/es.po
odoo/addons/product_restrict_payment_acquirer/i18n/it.po
odoo/addons/product_restrict_payment_acquirer/i18n/product_restrict_payment_acquirer.pot
odoo/addons/product_restrict_payment_acquirer/models/__init__.py
odoo/addons/product_restrict_payment_acquirer/models/payment_provider.py
odoo/addons/product_restrict_payment_acquirer/models/product_acquirer_settings.py
odoo/addons/product_restrict_payment_acquirer/models/product_template.py
odoo/addons/product_restrict_payment_acquirer/readme/DESCRIPTION.md
odoo/addons/product_restrict_payment_acquirer/readme/USAGE.md
odoo/addons/product_restrict_payment_acquirer/static/description/icon.png
odoo/addons/product_restrict_payment_acquirer/static/description/index.html
odoo/addons/product_restrict_payment_acquirer/tests/__init__.py
odoo/addons/product_restrict_payment_acquirer/tests/test_payment_acquirer.py
odoo/addons/product_restrict_payment_acquirer/views/product_template_views.xml
odoo/addons/product_restrict_payment_acquirer/views/res_config_settings_views.xml
odoo_addon_product_restrict_payment_acquirer-17.0.1.0.0.2.dist-info/METADATA
odoo_addon_product_restrict_payment_acquirer-17.0.1.0.0.2.dist-info/WHEEL
odoo_addon_product_restrict_payment_acquirer-17.0.1.0.0.2.dist-info/top_level.txt
odoo_addon_product_restrict_payment_acquirer-17.0.1.0.0.2.dist-info/RECORD
